pypi_all_names/__init__.py
pypi_all_names/cli.py
pypi_all_names/fetcher.py
pypi_all_names-1.0.0.dist-info/licenses/LICENSE
pypi_all_names-1.0.0.dist-info/METADATA
pypi_all_names-1.0.0.dist-info/WHEEL
pypi_all_names-1.0.0.dist-info/entry_points.txt
pypi_all_names-1.0.0.dist-info/top_level.txt
pypi_all_names-1.0.0.dist-info/RECORD
