Metadata-Version: 2.4
Name: pypi_all_names
Version: 1.0.0
Summary: Library to get all package names registered with PyPI at once!
Home-page: https://github.com/gaon12/pypi_all_names
Author: Jeong Gaon
Author-email: gokirito12@gmail.com
License: MIT
Classifier: License :: OSI Approved :: MIT License
Classifier: Programming Language :: Python :: 3
Classifier: Operating System :: OS Independent
Requires-Python: >=3.7
License-File: LICENSE
Requires-Dist: requests
Requires-Dist: beautifulsoup4
Dynamic: author
Dynamic: author-email
Dynamic: classifier
Dynamic: description
Dynamic: description-content-type
Dynamic: home-page
Dynamic: license
Dynamic: license-file
Dynamic: requires-dist
Dynamic: requires-python
Dynamic: summary
